hippu/__init__.py
hippu/_meta.py
hippu/errors.py
hippu/filter.py
hippu/http.py
hippu/request.py
hippu/response.py
hippu/server.py
hippu/service.py
hippu/stream.py
hippu/utils.py
hippu/filters/__init__.py
hippu/filters/cors.py
hippu/filters/gzipfilter.py
hippu-0.8.1.dist-info/LICENSE
hippu-0.8.1.dist-info/METADATA
hippu-0.8.1.dist-info/WHEEL
hippu-0.8.1.dist-info/top_level.txt
hippu-0.8.1.dist-info/RECORD
