Metadata-Version: 2.1
Name: hippu
Version: 0.8.1
Summary: Hippu - Micro HTTP Server
Home-page: https://gitlab.com/slaine/hippu.git/
Author: Sami Laine
Author-email: sami.jy.laine@gmail.com
License: BSD-3-Clause
Platform: UNKNOWN
